ment/__init__.py
ment/main.py
ment-0.2.5.dist-info/entry_points.txt
ment-0.2.5.dist-info/WHEEL
ment-0.2.5.dist-info/METADATA
ment-0.2.5.dist-info/RECORD
