Metadata-Version: 2.1
Name: ment
Version: 0.2.5
Summary: python library to write daily log in markdown quickly and to synthesize daily logs based on category
Home-page: https://github.com/kawagh/ment
Author: kawagh
Requires-Python: >=3.8,<4.0
Classifier: Programming Language :: Python :: 3
Classifier: Programming Language :: Python :: 3.10
Classifier: Programming Language :: Python :: 3.8
Classifier: Programming Language :: Python :: 3.9
Project-URL: Repository, https://github.com/kawagh/ment
